[{"name":"11","surname":"11","lastName":"11","contacts":[],"id":"1726132565121","updatedAt":"2024-09-12T09:16:05.121Z","createdAt":"2024-09-12T09:16:05.121Z"},{"name":"11","surname":"11222","lastName":"222","contacts":[],"id":"1726132615038","updatedAt":"2024-09-12T09:16:55.038Z","createdAt":"2024-09-12T09:16:55.038Z"},{"name":"qweqweqwq","surname":"qweqweqwe","lastName":"eeeee","contacts":[],"id":"1726133412219","updatedAt":"2024-09-12T09:30:12.220Z","createdAt":"2024-09-12T09:30:12.220Z"},{"name":"asdasda","surname":"asdasd","lastName":"sdasd","contacts":[],"id":"1726134501522","updatedAt":"2024-09-12T09:48:21.522Z","createdAt":"2024-09-12T09:48:21.522Z"},{"name":"gdfgdgdfg","surname":"dfgdsfgdf","lastName":"gggg","contacts":[],"id":"1726135374694","updatedAt":"2024-09-12T10:02:54.694Z","createdAt":"2024-09-12T10:02:54.694Z"},{"name":"wefsfs","surname":"rfhbvj","lastName":"11132311231231321312131","contacts":[],"id":"1726138783454","updatedAt":"2024-09-12T10:59:43.454Z","createdAt":"2024-09-12T10:59:43.454Z"}]